remedy_py/RemedyAPIClient.py
remedy_py/RemedyConstants.py
remedy_py/__init__.py
remedy_py/test.py
remedy_py/interface/__init__.py
remedy_py/interface/remedy_api.py
remedy_py-1.0.0.dist-info/LICENSE.txt
remedy_py-1.0.0.dist-info/METADATA
remedy_py-1.0.0.dist-info/WHEEL
remedy_py-1.0.0.dist-info/top_level.txt
remedy_py-1.0.0.dist-info/RECORD
