Metadata-Version: 2.1
Name: remedy-py
Version: 1.0.0
Summary: A python package used to interface with the BMC Remedy ITSM REST API
Home-page: https://github.com/breid1313/remedy-py
Author: Brian Reid
License: MIT
Platform: UNKNOWN
Classifier: Programming Language :: Python
Classifier: Programming Language :: Python :: 3.6
Requires-Dist: requests
